crossflow/__init__.py
crossflow/_version.py
crossflow/clients.py
crossflow/config.py
crossflow/filehandling.py
crossflow/kernels.py
crossflow/tasks.py
crossflow-0.1.2.dist-info/LICENSE.txt
crossflow-0.1.2.dist-info/METADATA
crossflow-0.1.2.dist-info/WHEEL
crossflow-0.1.2.dist-info/top_level.txt
crossflow-0.1.2.dist-info/RECORD
