Metadata-Version: 2.1
Name: crossflow
Version: 0.1.2
Summary: A Python workflows system
Home-page: 
Author: Charlie Laughton
Author-email: charles.laughton@nottingham.ac.uk
License: MIT license.
Classifier: Development Status :: 3 - Alpha
Classifier: Intended Audience :: Science/Research
Classifier: Environment :: Console
Classifier: License :: OSI Approved :: MIT License
Classifier: Programming Language :: Python
Classifier: Programming Language :: Python :: 3.4
Classifier: Programming Language :: Python :: 3.5
Classifier: Programming Language :: Python :: 3.6
Classifier: Programming Language :: Python :: 3.7
Classifier: Programming Language :: Python :: 3.8
Classifier: Topic :: Scientific/Engineering
Classifier: Operating System :: MacOS :: MacOS X
Classifier: Operating System :: POSIX
Classifier: Operating System :: Unix
License-File: LICENSE.txt
Requires-Dist: dask
Requires-Dist: distributed
Requires-Dist: fsspec
